hardwarelibrary/__init__.py
hardwarelibrary/__main__.py
hardwarelibrary/devicemanager.py
hardwarelibrary/echodevice.py
hardwarelibrary/notificationcenter.py
hardwarelibrary/physicaldevice.py
hardwarelibrary/utils.py
hardwarelibrary/.idea/vcs.xml
hardwarelibrary/.idea/workspace.xml
hardwarelibrary/.idea/inspectionProfiles/profiles_settings.xml
hardwarelibrary/cameras/__init__.py
hardwarelibrary/cameras/camera.py
hardwarelibrary/communication/__init__.py
hardwarelibrary/communication/commands.py
hardwarelibrary/communication/communicationport.py
hardwarelibrary/communication/debugport.py
hardwarelibrary/communication/diagnostics.py
hardwarelibrary/communication/echoport.py
hardwarelibrary/communication/serialport.py
hardwarelibrary/communication/usbport.py
hardwarelibrary/communication/.idea/.gitignore
hardwarelibrary/communication/.idea/communication.iml
hardwarelibrary/communication/.idea/misc.xml
hardwarelibrary/communication/.idea/modules.xml
hardwarelibrary/communication/.idea/vcs.xml
hardwarelibrary/communication/.idea/inspectionProfiles/profiles_settings.xml
hardwarelibrary/communication/libusb/Darwin/libusb-1.0.0.dylib
hardwarelibrary/communication/libusb/MS32/libusb-1.0.dll
hardwarelibrary/communication/libusb/MS64/libusb-1.0.dll
hardwarelibrary/daq/__init__.py
hardwarelibrary/daq/daqdevice.py
hardwarelibrary/daq/labjackdevice.py
hardwarelibrary/manuals/Cobolt-owners-manual-0401-D0105-A.pdf
hardwarelibrary/manuals/HR2000+-OEM-Data-Sheet.pdf
hardwarelibrary/manuals/MPC-325_OpMan.pdf
hardwarelibrary/manuals/Mightex CCD Line Camera Din8 Connector Description.pdf
hardwarelibrary/manuals/Mightex CCD Linear Camera User Manual.pdf
hardwarelibrary/manuals/TDS 1000B and TDS 2000B Manual.pdf
hardwarelibrary/manuals/Tektronix TDS-1002 Programming manual.pdf
hardwarelibrary/manuals/USB Primer.pdf
hardwarelibrary/manuals/USB2000+-OEM-Data-Sheet.pdf
hardwarelibrary/manuals/USB2000-OEM-Data-Sheet.pdf
hardwarelibrary/manuals/User_Manual_Integra_V3.0.pdf
hardwarelibrary-1.0.7.dist-info/METADATA
hardwarelibrary-1.0.7.dist-info/WHEEL
hardwarelibrary-1.0.7.dist-info/top_level.txt
hardwarelibrary-1.0.7.dist-info/RECORD
