Metadata-Version: 2.1
Name: hardwarelibrary
Version: 1.0.7
Summary: Cross-platform (macOS, Windows, Linux, etc...) library to control various hardware devices mostly for scientific applications.
Author-email: Daniel Cote <dccote@cervo.ulaval.ca>
License: MIT
Project-URL: Homepage, https://github.com/DCC-Lab/PyHardwareLibrary
Keywords: hardware,devices,usb,communication,app,control,spectrometer,powermeter,camera
Classifier: Development Status :: 4 - Beta
Classifier: Intended Audience :: Science/Research
Classifier: Intended Audience :: Education
Classifier: Topic :: Scientific/Engineering :: Physics
Classifier: Topic :: Education
Classifier: License :: OSI Approved :: MIT License
Classifier: Programming Language :: Python
Classifier: Programming Language :: Python :: 3
Classifier: Programming Language :: Python :: 3.7
Classifier: Operating System :: OS Independent
Requires-Python: >=3.7
Requires-Dist: numpy
Requires-Dist: matplotlib
Requires-Dist: pyserial
Requires-Dist: pyusb
Requires-Dist: pyftdi
Requires-Dist: LabJackPython
